gmpyinfr_amqp/__init__.py
gmpyinfr_amqp/amqp/__init__.py
gmpyinfr_amqp/utils/__init__.py
gmpyinfr_amqp-0.0.2.dist-info/LICENSE
gmpyinfr_amqp-0.0.2.dist-info/METADATA
gmpyinfr_amqp-0.0.2.dist-info/WHEEL
gmpyinfr_amqp-0.0.2.dist-info/top_level.txt
gmpyinfr_amqp-0.0.2.dist-info/RECORD
